Workbook

Sheet Chi tiết bảng NV
A1: DANH SÁCH CHI TIẾT BẢNG NGHIỆP VỤ
A2: STT | B2: Tên bảng | C2: Mô tả | D2: Phân hệ | E2: Loại | F2: Logical Object (Thiết kế)
A3: 1 | B3: COUNTRY | C3: Lưu thông tin mã quốc gia; tên tiếng việt; tên tiếng anh | D3: Danh mục điện tử dùng chung (Q2) | E3: Danh mục | F3: Location
A4: 2 | B4: REGION | C4: Lưu thông tin mã vùng; tên phân hệ; trạng thái (1: active, 0: unactive) | D4: Danh mục điện tử dùng chung (Q2) | E4: Danh mục | F4: Location
A5: 3 | B5: PROVINCE_NEW | C5: Lưu thông tin mã tỉnh/thành phố'; tên tiếng việt; tên tiếng anh | D5: Danh mục điện tử dùng chung (Q2) | E5: Danh mục | F5: Location
A6: 4 | B6: PROVINCE_OLD | C6: Lưu thông tin mã tỉnh/thành phố'; tên tiếng việt; tên tiếng anh | D6: Danh mục điện tử dùng chung (Q2) | E6: Danh mục | F6: Location
A7: 5 | B7: DISTRICT_OLD | C7: Lưu thông tin mã quận/huyện; tên phân hệ; stable id tỉnh/thành phố cũ (tham chiếu province_old.stableid) | D7: Danh mục điện tử dùng chung (Q2) | E7: Danh mục | F7: Location
A8: 6 | B8: WARD_NEW | C8: Lưu thông tin mã phường/xã; tên tiếng việt; tên tiếng anh | D8: Danh mục điện tử dùng chung (Q2) | E8: Danh mục | F8: Location
A9: 7 | B9: WARD_OLD | C9: Lưu thông tin mã phường/xã'; tên tiếng việt; tên tiếng anh | D9: Danh mục điện tử dùng chung (Q2) | E9: Danh mục | F9: Location
A10: 8 | B10: CURRENCY | C10: lưu danh sách danh mục tiền tệ | D10: Danh mục điện tử dùng chung (Q2) | E10: Danh mục | F10: Classification
A11: 9 | B11: DEPARTMENT | C11: lưu danh sách danh mục phòng ban | D11: Danh mục điện tử dùng chung (Q2) | E11: Danh mục | F11: Classification
A12: 10 | B12: ENTERPRISE_TYPE | C12: Danh mục loại: mã phòng ban; tên phòng ban; nhãn hiển thị | D12: Danh mục điện tử dùng chung (Q2) | E12: Danh mục | F12: Classification
A13: 11 | B13: SECURITY_TYPE | C13: Danh mục loại: mã loại chứng khoán (auto: lck-{seq}); tên loại chứng khoán; trạng thái hoạt động (1: đang sử dụng, 0: không sử dụng) | D13: Danh mục điện tử dùng chung (Q2) | E13: Danh mục | F13: Classification
A14: 12 | B14: MARKET | C14: Lưu thông tin mã thị trường; tên thị trường; trạng thái hoạt động (1: đang sử dụng, 0: không sử dụng) | D14: Danh mục điện tử dùng chung (Q2) | E14: Danh mục | F14: Classification
... A89: 87 | B89: CAT_WARD | C89: Danh mục phường/xã | D89: Giám sát CTCK (SCMS) | E89: Danh mục | F89: Location
A90: 88 | B90: ALERT_FINANCIAL_INDICATOR | C90: Chỉ tiêu tài chính cảnh báo | D90: Giám sát CTCK (SCMS) | E90: Nghiệp vụ
A91: 89 | B91: ALERT_INDICATOR | C91: Chỉ tiêu cảnh báo | D91: Giám sát CTCK (SCMS) | E91: Nghiệp vụ
A92: 90 | B92: ALERT_INDICATOR_CONDITION | C92: Điều kiện kích hoạt cảnh báo chỉ tiêu | D92: Giám sát CTCK (SCMS) | E92: Hệ thống
A93: 91 | B93: ALERT_RUN | C93: Lần chạy cảnh báo | D93: Giám sát CTCK (SCMS) | E93: Hệ thống
A94: 92 | B94: AUDITOR | C94: Kiểm toán viên | D94: Giám sát CTCK (SCMS) | E94: Danh mục
A95: 93 | B95: BANK | C95: Thông tin ngân hàng: tên, mã, địa chỉ, trạng thái hoạt động | D95: Giám sát CTCK (SCMS) | E95: Danh mục
A96: 94 | B96: BANK_PERIODIC_REPORT | C96: Báo cáo định kỳ ngân hàng | D96: Giám sát CTCK (SCMS) | E96: Nghiệp vụ
A97: 95 | B97: CUSTODIAN_BANK | C97: Ngân hàng lưu ký | D97: Giám sát CTCK (SCMS) | E97: Danh mục
A98: 96 | B98: DISCLOSURE_NEWS | C98: Tin tức công bố thông tin | D98: Giám sát CTCK (SCMS) | E98: Nghiệp vụ
A99: 97 | B99: DISCLOSURE_NEWS_FILE | C99: Tệp đính kèm tin tức CBTT | D99: Giám sát CTCK (SCMS) | E99: Hệ thống
A100: 98 | B100: DISCLOSURE_REPORT | C100: Báo cáo công bố thông tin | D100: Giám sát CTCK (SCMS) | E100: Nghiệp vụ
A101: 99 | B101: DISCLOSURE_SECURITIES_OFFERING | C101: Thông tin chào bán chứng khoán | D101: Giám sát CTCK (SCMS) | E101: Nghiệp vụ
... A193: 191 | B193: MEMBER_REPORT_HISTORY | C193: Lịch sử báo cáo của đơn vị thành viên | D193: Giám sát CTCK (SCMS) | E193: Lịch sử
A194: 192 | B194: AGENCY_TYPE | C194: Danh mục loại đại lý phân phối | D194: Giám sát CT QLQ & Quỹ ĐT (FMS) | E194: Danh mục | F194: Classification
A195: 193 | B195: BUSINESS | C195: Danh mục ngành nghề kinh doanh | D195: Giám sát CT QLQ & Quỹ ĐT (FMS) | E195: Danh mục | F195: Classification
A196: 194 | B196: BUSINESS_TYPE | C196: Danh mục loại hình kinh doanh | D196: Giám sát CT QLQ & Quỹ ĐT (FMS) | E196: Danh mục | F196: Classification
A197: 195 | B197: COMPANY_TYPE | C197: Danh mục loại hình công ty | D197: Giám sát CT QLQ & Quỹ ĐT (FMS) | E197: Danh mục | F197: Classification
A198: 196 | B198: FUND_TYPE | C198: Danh mục loại quỹ đầu tư | D198: Giám sát CT QLQ & Quỹ ĐT (FMS) | E198: Danh mục | F198: Classification
A199: 197 | B199: LOCATION | C199: Danh sách tỉnh/thành phố | D199: Giám sát CT QLQ & Quỹ ĐT (FMS) | E199: Danh mục | F199: Location
A200: 198 | B200: NATIONAL | C200: Danh sách quốc gia/quốc tịch | D200: Giám sát CT QLQ & Quỹ ĐT (FMS) | E200: Danh mục | F200: Location
A201: 199 | B201: PAR_VALUE | C201: Danh sách mệnh giá cổ phần/chứng chỉ quỹ | D201: Giám sát CT QLQ & Quỹ ĐT (FMS) | E201: Danh mục | F201: Classification
A202: 200 | B202: RELATION | C202: Danh mục mối quan hệ giữa các bên | D202: Giám sát CT QLQ & Quỹ ĐT (FMS) | E202: Danh mục | F202: Classification
A203: 201 | B203: STATUS | C203: Danh mục trạng thái hoạt động | D203: Giám sát CT QLQ & Quỹ ĐT (FMS) | E203: Danh mục | F203: Classification
A204: 202 | B204: STOCKHOLDER_TYPE | C204: Danh mục loại hình nhà đầu tư/cổ đông | D204: Giám sát CT QLQ & Quỹ ĐT (FMS) | E204: Danh mục | F204: Classification
A205: 203 | B205: FUND_TYPE | C205: Danh mục loại quỹ đầu tư | D205: Giám sát CT QLQ & Quỹ ĐT (FMS) | E205: Danh mục | F205: Classification
A206: 204 | B206: DT_SCOPE | C206: Phân quyền dữ liệu – phạm vi truy cập | D206: Giám sát CT QLQ & Quỹ ĐT (FMS) | E206: Hệ thống
A207: 205 | B207: DT_SC_SEC | C207: Phân quyền dữ liệu công ty QLQ cho chuyên viên | D207: Giám sát CT QLQ & Quỹ ĐT (FMS) | E207: Hệ thống
A208: 206 | B208: JOB_TYPE | C208: Danh mục loại chức vụ | D208: Giám sát CT QLQ & Quỹ ĐT (FMS) | E208: Danh mục
A209: 207 | B209: SECURITIES | C209: Danh sách công ty QLQ trong nước | D209: Giám sát CT QLQ & Quỹ ĐT (FMS) | E209: Nghiệp vụ
A210: 208 | B210: SEC_BUP | C210: Lịch sử chi tiết công ty QLQ (2 bản ghi trước/sau) | D210: Giám sát CT QLQ & Quỹ ĐT (FMS) | E210: Lịch sử
A211: 209 | B211: SEC_BUSINESS | C211: Ngành nghề kinh doanh của công ty QLQ | D211: Giám sát CT QLQ & Quỹ ĐT (FMS) | E211: Nghiệp vụ
A212: 210 | B212: SEC_FUND_MANAGER | C212: Ánh xạ người quản lý quỹ và công ty QLQ | D212: Giám sát CT QLQ & Quỹ ĐT (FMS) | E212: Nghiệp vụ
A213: 211 | B213: BRANCHS | C213: Danh sách CN/VPĐD công ty QLQ trong nước | D213: Giám sát CT QLQ & Quỹ ĐT (FMS) | E213: Nghiệp vụ
A214: 212 | B214: BRA_BUSINESS | C214: Ngành nghề kinh doanh của CN/VPĐD công ty QLQ | D214: Giám sát CT QLQ & Quỹ ĐT (FMS) | E214: Nghiệp vụ
A215: 213 | B215: BRCH_BUP | C215: Lịch sử chi tiết CN/VPĐD công ty QLQ trong nước | D215: Giám sát CT QLQ & Quỹ ĐT (FMS) | E215: Lịch sử
A216: 214 | B216: FOR_BRCH | C216: Danh sách VPĐD/CN công ty QLQ NN tại VN | D216: Giám sát CT QLQ & Quỹ ĐT (FMS) | E216: Nghiệp vụ
A217: 215 | B217: FG_BR_BUP | C217: Lịch sử chi tiết VPĐD/CN công ty QLQ NN tại VN | D217: Giám sát CT QLQ & Quỹ ĐT (FMS) | E217: Lịch sử
... A320: 318 | B320: TRANSFER_AGENT_HISTORY | C320: Lịch sử thông tin đại lý chuyển nhượng quỹ hưu trí | D320: Giám sát CT QLQ & Quỹ ĐT (FMS) | E320: Lịch sử
A321: 319 | B321: LOCATION | C321: Danh sách tỉnh/thành phố | D321: Giám sát NĐT nước ngoài (FIMS) | E321: Danh mục | F321: Location
A322: 320 | B322: NATIONAL | C322: Danh sách quốc gia/quốc tịch | D322: Giám sát NĐT nước ngoài (FIMS) | E322: Danh mục | F322: Location
A323: 321 | B323: STATUS | C323: Danh mục trạng thái hoạt động | D323: Giám sát NĐT nước ngoài (FIMS) | E323: Danh mục | F323: Classification
A324: 322 | B324: JOBTYPE | C324: Lưu danh sách chức vụ của người dùng trên hệ thống | D324: Giám sát NĐT nước ngoài (FIMS) | E324: Danh mục | F324: Classification
A325: 323 | B325: SECURITIESTYPE | C325: Lưu danh sách loại chứng khoán | D325: Giám sát NĐT nước ngoài (FIMS) | E325: Danh mục | F325: Classification
A326: 324 | B326: SECURITIES | C326: Danh sách công ty QLQ trong nước | D326: Giám sát NĐT nước ngoài (FIMS) | E326: Danh mục | F326: FundManagementCompany
A327: 325 | B327: STOCKHOLDERTYPE | C327: Lưu danh sách danh mục loại cổ đông | D327: Giám sát NĐT nước ngoài (FIMS) | E327: Danh mục | F327: Classification
A328: 326 | B328: COMPANYTYPE | C328: Lưu danh sách danh mục loại hình doanh nghiệp | D328: Giám sát NĐT nước ngoài (FIMS) | E328: Danh mục | F328: Classification
A329: 327 | B329: BUSINESS | C329: Danh mục ngành nghề kinh doanh | D329: Giám sát NĐT nước ngoài (FIMS) | E329: Danh mục | F329: Classification
A330: 328 | B330: CURRENCY | C330: lưu danh sách danh mục tiền tệ | D330: Giám sát NĐT nước ngoài (FIMS) | E330: Danh mục | F330: Classification
A331: 329 | B331: DEGREE | C331: lưu danh sách danh mục trình độ | D331: Giám sát NĐT nước ngoài (FIMS) | E331: Danh mục | F331: Classification
A332: 330 | B332: UNIT | C332: lưu danh sách danh mục đơn vị | D332: Giám sát NĐT nước ngoài (FIMS) | E332: Danh mục | F332: Classification
... A344: 342 | B344: RPT_EVENT_TYPE_STATUS_LINK | C344: Lưu liên kết trạng thái loại sự vụ | D344: Giám sát NĐT nước ngoài (FIMS) | E344: Danh mục | F344: Classification
A345: 343 | B345: RPTTEMP | C345: lưu danh sách biểu mẫu báo cáo đầu vào | D345: Giám sát NĐT nước ngoài (FIMS) | E345: Báo cáo động
A346: 344 | B346: SHEET | C346: Danh sách sheet biểu mẫu báo cáo đầu vào | D346: Giám sát NĐT nước ngoài (FIMS) | E346: Báo cáo động
A347: 345 | B347: RPTPERIOD | C347: lưu danh sách kỳ của báo cáo đầu vào | D347: Giám sát NĐT nước ngoài (FIMS) | E347: Báo cáo động
A348: 346 | B348: RPTPDSHT | C348: bảng trung gian giữa bảng SHEET và bảng RPTPERIOD | D348: Giám sát NĐT nước ngoài (FIMS) | E348: Báo cáo động
A349: 347 | B349: RPTTPOUT | C349: lưu danh sách biểu mẫu báo cáo đầu ra | D349: Giám sát NĐT nước ngoài (FIMS) | E349: Báo cáo động
A350: 348 | B350: SHEETOUT | C350: lưu danh sách sheet của báo cáo đầu ra | D350: Giám sát NĐT nước ngoài (FIMS) | E350: Báo cáo động
A351: 349 | B351: SECURITIESACCOUNT | C351: Lưu danh sách tài khoản giao dịch chứng khoán | D351: Giám sát NĐT nước ngoài (FIMS) | E351: Nghiệp vụ
A352: 350 | B352: RELATIONSHIP | C352: Lưu danh sách quan hệ | D352: Giám sát NĐT nước ngoài (FIMS) | E352: Nghiệp vụ
A353: 351 | B353: CLOSING_PRICE_SECURITIES | C353: Lưu giá đóng cửa chứng khoán | D353: Giám sát NĐT nước ngoài (FIMS) | E353: Nghiệp vụ
A354: 352 | B354: STOCKEXCHANGE | C354: Lưu danh sách đối tượng gửi báo cáo là Sở giao dịch | D354: Giám sát NĐT nước ngoài (FIMS) | E354: Nghiệp vụ
A355: 353 | B355: DEPOSITORYCENTER | C355: Lưu danh sách đối tượng gửi báo cáo là Trung tâm lưu ký | D355: Giám sát NĐT nước ngoài (FIMS) | E355: Nghiệp vụ
A356: 354 | B356: FUNDCOMPANY | C356: Lưu danh sách đối tượng gửi báo cáo là Công ty quản lý quỹ | D356: Giám sát NĐT nước ngoài (FIMS) | E356: Nghiệp vụ
... A388: 386 | B388: TRADINGAUTHORIZATIONINVESHIS | C388: Lưu lịch sử NĐT NN trong ủy quyền giao dịch | D388: Giám sát NĐT nước ngoài (FIMS) | E388: Lịch sử
A389: 387 | B389: BANKS | C389: Danh mục ngân hàng (dùng cho nộp phí thi): mã ngân hàng, tên đầy đủ, tên viết tắt, tên tiếng Anh, mã giao dịch | D389: Người hành nghề chứng khoán (NHNCK) | E389: Danh mục | F389: Bank
A390: 388 | B390: COUNTRIES | C390: Danh mục quốc gia/quốc tịch: mã quốc gia, tên quốc gia, cờ mặc định (Việt Nam), trạng thái | D390: Người hành nghề chứng khoán (NHNCK) | E390: Danh mục | F390: Location
A391: 389 | B391: DISTRICTS | C391: Danh mục quận/huyện: mã huyện, tên huyện, loại (huyện/quận/thị xã/thành phố thuộc tỉnh), trạng thái | D391: Người hành nghề chứng khoán (NHNCK) | E391: Danh mục | F391: Location
A392: 390 | B392: EDUCATION_LEVELS | C392: Danh mục trình độ học vấn: tên trình độ, hiển thị trên giao diện, cờ dữ liệu gốc, trạng thái | D392: Người hành nghề chứng khoán (NHNCK) | E392: Danh mục | F392: Classification
A393: 391 | B393: FORMS | C393: Biểu mẫu liên quan đến quy trình cấp CCHN: tên biểu mẫu, căn cứ pháp lý, file tải về, trạng thái, nổi bật | D393: Người hành nghề chứng khoán (NHNCK) | E393: Danh mục | F393: Classification
A394: 392 | B394: LEGAL_DOCUMENTS | C394: Văn bản pháp lý về hành nghề chứng khoán: số văn bản, tên, cơ quan ban hành, ngày ban hành, file, trạng thái, nổi bật | D394: Người hành nghề chứng khoán (NHNCK) | E394: Danh mục | F394: Classification
A395: 393 | B395: POSITIONS | C395: Danh mục chức vụ của cán bộ UBCKNN: tên chức vụ, trạng thái | D395: Người hành nghề chứng khoán (NHNCK) | E395: Danh mục | F395: Classification
A396: 394 | B396: PROCEDURES | C396: Thủ tục hành chính cấp CCHN: loại thủ tục, tiêu đề, nội dung, thời gian xử lý, đối tượng, cơ quan thực hiện, kết quả, phí | D396: Người hành nghề chứng khoán (NHNCK) | E396: Danh mục | F396: Classification
A397: 395 | B397: PROVINCES | C397: Danh mục tỉnh/thành phố trực thuộc quốc gia: mã tỉnh, tên tỉnh, loại (tỉnh/thành phố), trạng thái | D397: Người hành nghề chứng khoán (NHNCK) | E397: Danh mục | F397: Location
A398: 396 | B398: SPECIALIZATIONS | C398: Danh mục chuyên ngành CCHN: mã chuyên ngành, tên, căn cứ pháp lý, mã TTHC tương ứng, trạng thái | D398: Người hành nghề chứng khoán (NHNCK) | E398: Danh mục | F398: Classification
A399: 397 | B399: SPECIALIZATION_COURSES | C399: Lớp học chứng chỉ chuyên môn theo từng chuyên ngành: năm học, mã lớp, tên lớp, thời gian thi, địa điểm, tỉnh tổ chức | D399: Người hành nghề chứng khoán (NHNCK) | E399: Danh mục | F399: Classification
A400: 398 | B400: SPECIALIZATION_COURSE_DETAILS | C400: Kết quả thi chứng chỉ chuyên môn của từng học viên trong lớp: điểm thi, kết quả, thông tin cá nhân học viên | D400: Người hành nghề chứng khoán (NHNCK) | E400: Danh mục | F400: Classification
A401: 399 | B401: UNITS | C401: Đơn vị tổ chức nội bộ UBCKNN: cây phân cấp đơn vị, mã đơn vị, tên, địa chỉ, điện thoại, email, fax | D401: Người hành nghề chứng khoán (NHNCK) | E401: Danh mục | F401: Classification
A402: 400 | B402: APPLICATIONS | C402: Hồ sơ đề nghị cấp/cấp lại CCHN: loại đăng ký, loại hồ sơ, mã hồ sơ, ngày nộp, lý do cấp lại, kết quả, trạng thái xử lý, thông tin nhận chứng chỉ | D402: Người hành nghề chứng khoán (NHNCK) | E402: Nghiệp vụ
A403: 401 | B403: APPLICATION_ARCHIVES | C403: Thông tin lưu trữ vật lý hồ sơ CCHN: địa điểm lưu trữ, người liên hệ, điện thoại, ghi chú lưu trữ | D403: Người hành nghề chứng khoán (NHNCK) | E403: Nghiệp vụ
A404: 402 | B404: APPLICATION_DECISIONS | C404: Liên kết hồ sơ CCHN với quyết định tương ứng (một quyết định có thể áp dụng cho nhiều hồ sơ) | D404: Người hành nghề chứng khoán (NHNCK) | E404: Nghiệp vụ
A405: 403 | B405: APPLICATION_DOCUMENTS | C405: Tài liệu đính kèm trong hồ sơ CCHN: loại tài liệu, trạng thái thẩm định, file đính kèm, người thẩm định, ghi chú | D405: Người hành nghề chứng khoán (NHNCK) | E405: Nghiệp vụ
A406: 404 | B406: APPLICATION_EXPERIENCES | C406: Kinh nghiệm làm việc khai báo trong hồ sơ xin cấp CCHN: tổ chức, phòng ban, thời gian, hợp đồng lao động, xác nhận của giám đốc | D406: Người hành nghề chứng khoán (NHNCK) | E406: Nghiệp vụ
A407: 405 | B407: APPLICATION_FEES | C407: Thông tin lệ phí nộp hồ sơ CCHN: loại phí, số tiền, ngày yêu cầu, ngày thanh toán, ngày hết hạn, trạng thái, file chứng từ | D407: Người hành nghề chứng khoán (NHNCK) | E407: Nghiệp vụ
A408: 406 | B408: APPLICATION_GROUPS | C408: Nhóm hồ sơ CCHN xử lý tập thể (dạng batch): tên nhóm, số lượng hồ sơ, ngày tạo nhóm, ngày hoàn thành, quyết định ban hành | D408: Người hành nghề chứng khoán (NHNCK) | E408: Nghiệp vụ
A409: 407 | B409: APPLICATION_GROUP_MEMBERS | C409: Thành viên (hồ sơ) trong nhóm xử lý tập thể: hồ sơ nào thuộc nhóm nào, trạng thái, thứ tự | D409: Người hành nghề chứng khoán (NHNCK) | E409: Nghiệp vụ
...

Sheet Chi tiết bảng HT
A1: DANH SÁCH CHI TIẾT BẢNG HỆ THỐNG (461 bảng – để review)
A2: STT | B2: Tên bảng | C2: Mô tả | D2: Nhóm bảng | E2: Phân hệ | F2: Phân loại hệ thống | G2: Ghi chú (review)
A3: 1 | B3: DATABASECHANGELOG | C3: Lưu thông tin người viết changeset; file chứa changeset; thời điểm changeset được chạy | D3: Mô tả chung | E3: Danh mục điện tử dùng chung (Q2) | F3: Migration / Schema version
A4: 2 | B4: DATABASECHANGELOGLOCK | C4: Lưu thông tin trạng thái lock (1: khóa, 0: không khóa); thời điểm lock được cấp; thông tin người log | D4: Mô tả chung | E4: Danh mục điện tử dùng chung (Q2) | F4: Migration / Schema version
A5: 3 | B5: LOG_DATA_CHANGES | C5: Lưu thông tin tên application; client ip; username | D5: Mô tả chung | E5: Danh mục điện tử dùng chung (Q2) | F5: Log / Audit
A6: 4 | B6: AUDIT_FIRM | C6: Công ty kiểm toán | D6: Nhóm bảng AUDIT – Kiểm toán | E6: Giám sát CTCK (SCMS) | F6: Log / Audit
A7: 5 | B7: DIGITAL_CERTIFICATE | C7: Chứng thư số | D7: Nhóm bảng CERT – Chứng thư số | E7: Giám sát CTCK (SCMS) | F7: Chứng thư số / Token
A8: 6 | B8: LNK_FUNCTION_USER | C8: Liên kết chức năng và người dùng | D8: Nhóm bảng LNK – Liên kết & Phân quyền | E8: Giám sát CTCK (SCMS) | F8: Quản lý người dùng
A9: 7 | B9: LNK_FUNCTION_USER_GROUP | C9: Liên kết chức năng và nhóm người dùng | D9: Nhóm bảng LNK – Liên kết & Phân quyền | E9: Giám sát CTCK (SCMS) | F9: Quản lý người dùng
A10: 8 | B10: PERMISSION_DATA | C10: Phân quyền dữ liệu | D10: Nhóm bảng LNK – Liên kết & Phân quyền | E10: Giám sát CTCK (SCMS) | F10: Phân quyền / Vai trò
A11: 9 | B11: PERMISSION_INPUT_REPORT | C11: Phân quyền nhập liệu báo cáo | D11: Nhóm bảng LNK – Liên kết & Phân quyền | E11: Giám sát CTCK (SCMS) | F11: Phân quyền / Vai trò
A12: 10 | B12: PERMISSION_INPUT_REPORT_EVENT | C12: Phân quyền sự kiện nhập liệu báo cáo | D12: Nhóm bảng LNK – Liên kết & Phân quyền | E12: Giám sát CTCK (SCMS) | F12: Phân quyền / Vai trò
A13: 11 | B13: PERMISSION_OUTPUT_REPORT | C13: Phân quyền khai thác báo cáo | D13: Nhóm bảng LNK – Liên kết & Phân quyền | E13: Giám sát CTCK (SCMS) | F13: Phân quyền / Vai trò
A14: 12 | B14: PERMISSION_OUTPUT_REPORT_FORM | C14: Phân quyền biểu mẫu báo cáo khai thác | D14: Nhóm bảng LNK – Liên kết & Phân quyền | E14: Giám sát CTCK (SCMS) | F14: Phân quyền / Vai trò
... A223: 221 | B223: INVESTOR_ACCOUNT_DASHBOARD | C223: Lưu thông tin thời điểm job lấy dữ liệu; tổng số tài khoản; số tài khoản mở | D223: Phân hệ Giám sát giao dịch chứng khoán | E223: Giám sát giao dịch chứng khoán (Q5) | F223: Hệ thống khác
A224: nfnnfsdnnfnewjnf | B224: BUSINESS_DASHBOARD | C224: Lưu thông tin thời điểm job lấy dữ liệu; số lượng sự kiện của tổ chức niêm yết cần phê duyệt; số lượng tổ chức niêm yết | D224: Phân hệ Giám sát giao dịch chứng khoán | E224: Giám sát giao dịch chứng khoán (Q5) | F224: Hệ thống khác
A225: 223 | B225: PERMISSION_GROUP | C225: Lưu thông tin tên nhóm quyền; mô tả | D225: Phân hệ Quản lý rủi ro về thị trường chứng khoán | E225: Quản lý rủi ro TTCK (Q16) | F225: Phân quyền / Vai trò
A226: 224 | B226: PERMISSION_GROUP_USER | C226: Lưu thông tin người dùng được phân quyền (user id); mã người dùng; tên người dùng được phân quyền | D226: Phân hệ Quản lý rủi ro về thị trường chứng khoán | E226: Quản lý rủi ro TTCK (Q16) | F226: Quản lý người dùng
A227: 225 | B227: PERMISSION_GROUP_INDICATOR | C227: Lưu thông tin chỉ tiêu (indicator id) | D227: Phân hệ Quản lý rủi ro về thị trường chứng khoán | E227: Quản lý rủi ro TTCK (Q16) | F227: Phân quyền / Vai trò
A228: 226 | B228: REPORT_PERMISSION_GROUP | C228: Lưu thông tin mã nhóm phân quyền; tên nhóm phân quyền; trạng thái: draft, active, expired, cancelled | D228: Phân hệ Thống kê nội bộ | E228: Thống kê nội bộ (Q15) | F228: Phân quyền / Vai trò
A229: 227 | B229: AUDIT_LOG | C229: Nhật ký: tên đăng nhập; loại thực thể; mô tả hành động | D229: Phân hệ Thống kê nội bộ | E229: Thống kê nội bộ (Q15) | F229: Log / Audit
A230: 228 | B230: USER_PERMISSIONS_GROUP | D230: Phân hệ Thống kê nội bộ | E230: Thống kê nội bộ (Q15) | F230: Quản lý người dùng
A231: 229 | B231: HT_THAM_SO | C231: Lưu các thông tin về tham số hệ thống | D231: Nhóm dữ liệu Quản trị hệ thống | E231: Kết nối trao đổi dữ liệu (Q19) | F231: Quản trị hệ thống
A232: 230 | B232: NHAT_KY_HE_THONG | C232: Lưu các thông tin về nhật ký phân hệ, các thao tác của người dùng trên phân hệ | D232: Nhóm dữ liệu Quản trị hệ thống | E232: Kết nối trao đổi dữ liệu (Q19) | F232: Quản trị hệ thống
A233: 231 | B233: THIET_LAP_LICH | C233: Bảng lưu cấu hình lịch truyền/ nhận dữ liệu giữa UBCKNN và Cục Thuế | D233: Nhóm dữ liệu Quản trị hệ thống | E233: Kết nối trao đổi dữ liệu (Q19) | F233: Job / Scheduler
A234: 232 | B234: DB_LOG | C234: Bảng lưu log truy vấn trên database | D234: Nhóm dữ liệu Quản trị hệ thống | E234: Kết nối trao đổi dữ liệu (Q19) | F234: Log / Audit
A235: 233 | B235: LOGINS | C235: Bảng tài khoản đăng nhập | D235: 2.1.1 Các mô hình quan hệ dữ liệu | E235: IDS – Hệ thống dữ liệu nhận dạng tổ chức | F235: Quản lý người dùng
A236: 234 | B236: USER_AUDIT_LOG | C236: Bảng lưu log người dùng thao tác trên hệ thống | D236: 2.1.1 Các mô hình quan hệ dữ liệu | E236: IDS – Hệ thống dữ liệu nhận dạng tổ chức | F236: Quản lý người dùng
A237: 235 | B237: NOTIFICATIONS | C237: Thông báo trong hệ thống NHNCK: loại thông báo, loại hành động, nội dung, liên kết, người nhận, thời gian gửi/đọc | D237: 2.1.1 Các mô hình quan hệ dữ liệu | E237: IDS – Hệ thống dữ liệu nhận dạng tổ chức | F237: Thông báo hệ thống
A238: 236 | B238: SYS_PARAMETERS | C238: Lưu trữ cấu hình tham số hệ thống | D238: 2.1.1 Các mô hình quan hệ dữ liệu | E238: IDS – Hệ thống dữ liệu nhận dạng tổ chức | F238: Cấu hình / Hạ tầng
A239: 237 | B239: INTG_REPORT_CONFIG | C239: Lưu thông tin cấu hình mẫu báo cáo cần đẩy lên IDS | D239: 2.1.1 Các mô hình quan hệ dữ liệu | E239: IDS – Hệ thống dữ liệu nhận dạng tổ chức | F239: Cấu hình / Hạ tầng
A240: 238 | B240: INTG_SIGNATURE_CONFIG | C240: Cấu hình master cho các lịch trình và chữ ký chứng khoán (HNX, HOSE) | D240: 2.1.1 Các mô hình quan hệ dữ liệu | E240: IDS – Hệ thống dữ liệu nhận dạng tổ chức | F240: Cấu hình / Hạ tầng
A241: 239 | B241: CONTENTITEMINDEX | C241: Orchard Core - chỉ mục chính của tất cả content item (loại, trạng thái publish, chủ sở hữu, ngày, đường dẫn) | D241: Noi dung va cau truc du lieu | E241: Thủ tục hành chính (TTHC) | F241: Platform hạ tầng (TTHC)
A242: 240 | B242: DOCUMENT | C242: Quản lý tài liệu đính kèm hồ sơ | D242: Noi dung va cau truc du lieu | E242: Thủ tục hành chính (TTHC) | F242: Platform hạ tầng (TTHC)
... A463: 461 | B463: TVRP_GA4_CONFIGS | C463: Cấu hình Google Analytics 4 - thông tin đăng nhập GA4 được mã hóa theo từng site | D463: TVRP - Khac | E463: Thủ tục hành chính (TTHC) | F463: Cấu hình / Hạ tầng

Sheet Kế hoạch
A1: PIVOT: LOẠI BẢNG × PHÂN HỆ | I1: Thiết kế bảng | K1: Thiết kế trường + mapping | M1: Lập trình Atomic
A2: Thiết kế Atomic | B2: Danh mục | C2: Nghiệp vụ | D2: Lịch sử | E2: Báo cáo động | F2: Tổng bảng chứa DL nghiệp vụ | G2: Phân loại | H2: Trạng thái | I2: Start | J2: End | K2: Start | L2: End | M2: Start | N2: End
A3: Danh mục điện tử dùng chung (Q2) | B3: =COUNTIFS('Chi tiết bảng NV'!$D$2:$D$1000,'Kế hoạch'!A3,'Chi tiết bảng NV'!$E$2:$E$1000,'Kế hoạch'!$B$2) -> 65 | C3: =COUNTIFS('Chi tiết bảng NV'!$D$2:$D$1000,'Kế hoạch'!A3,'Chi tiết bảng NV'!$E$2:$E$1000,'Kế hoạch'!$C$2) -> 0 | D3: =COUNTIFS('Chi tiết bảng NV'!$D$2:$D$1000,'Kế hoạch'!A3,'Chi tiết bảng NV'!$E$2:$E$1000,'Kế hoạch'!$D$2) -> 0 | E3: =COUNTIFS('Chi tiết bảng NV'!$D$2:$D$1000,'Kế hoạch'!A3,'Chi tiết bảng NV'!$E$2:$E$1000,$E$2) -> 0 | F3: =SUM(B3:E3) -> 65 | G3: Chỉ thiết kế ATM, Không lên DTM | H3: Đã thiết kế | I3: Done | J3: Done | K3: 46203 | L3: 46203 | M3: =L3+1 -> 46204 | N3: =M3+3 -> 46207
A4: Giám sát CTCK (SCMS) | B4: =COUNTIFS('Chi tiết bảng NV'!$D$2:$D$1000,'Kế hoạch'!A4,'Chi tiết bảng NV'!$E$2:$E$1000,'Kế hoạch'!$B$2) -> 29 | C4: =COUNTIFS('Chi tiết bảng NV'!$D$2:$D$1000,'Kế hoạch'!A4,'Chi tiết bảng NV'!$E$2:$E$1000,'Kế hoạch'!$C$2) -> 57 | D4: =COUNTIFS('Chi tiết bảng NV'!$D$2:$D$1000,'Kế hoạch'!A4,'Chi tiết bảng NV'!$E$2:$E$1000,'Kế hoạch'!$D$2) -> 12 | E4: =COUNTIFS('Chi tiết bảng NV'!$D$2:$D$1000,'Kế hoạch'!A4,'Chi tiết bảng NV'!$E$2:$E$1000,$E$2) -> 19 | F4: =SUM(B4:E4) -> 117 | H4: Xong thiết kế mức bảng | I4: Done | J4: Done | K4: 46203 | L4: 46204 | M4: =L4+1 -> 46205 | N4: =M4+3 -> 46208
A5: Giám sát CT QLQ & Quỹ ĐT (FMS) | B5: =COUNTIFS('Chi tiết bảng NV'!$D$2:$D$1000,'Kế hoạch'!A5,'Chi tiết bảng NV'!$E$2:$E$1000,'Kế hoạch'!$B$2) -> 13 | C5: =COUNTIFS('Chi tiết bảng NV'!$D$2:$D$1000,'Kế hoạch'!A5,'Chi tiết bảng NV'!$E$2:$E$1000,'Kế hoạch'!$C$2) -> 59 | D5: =COUNTIFS('Chi tiết bảng NV'!$D$2:$D$1000,'Kế hoạch'!A5,'Chi tiết bảng NV'!$E$2:$E$1000,'Kế hoạch'!$D$2) -> 28 | E5: =COUNTIFS('Chi tiết bảng NV'!$D$2:$D$1000,'Kế hoạch'!A5,'Chi tiết bảng NV'!$E$2:$E$1000,$E$2) -> 10 | F5: =SUM(B5:E5) -> 110 | I5: 46203 | J5: 46203 | K5: 46205 | L5: =J5+3 -> 46206 | M5: =L5+1 -> 46207 | N5: =M5+3 -> 46210
A6: Giám sát NĐT nước ngoài (FIMS) | B6: =COUNTIFS('Chi tiết bảng NV'!$D$2:$D$1000,'Kế hoạch'!A6,'Chi tiết bảng NV'!$E$2:$E$1000,'Kế hoạch'!$B$2) -> 24 | C6: =COUNTIFS('Chi tiết bảng NV'!$D$2:$D$1000,'Kế hoạch'!A6,'Chi tiết bảng NV'!$E$2:$E$1000,'Kế hoạch'!$C$2) -> 26 | D6: =COUNTIFS('Chi tiết bảng NV'!$D$2:$D$1000,'Kế hoạch'!A6,'Chi tiết bảng NV'!$E$2:$E$1000,'Kế hoạch'!$D$2) -> 10 | E6: =COUNTIFS('Chi tiết bảng NV'!$D$2:$D$1000,'Kế hoạch'!A6,'Chi tiết bảng NV'!$E$2:$E$1000,$E$2) -> 8 | F6: =SUM(B6:E6) -> 68 | I6: 46203 | J6: 46203 | K6: 46205 | L6: =J6+3 -> 46206 | M6: =L6+1 -> 46207 | N6: =M6+3 -> 46210
A7: Người hành nghề chứng khoán (NHNCK) | B7: =COUNTIFS('Chi tiết bảng NV'!$D$2:$D$1000,'Kế hoạch'!A7,'Chi tiết bảng NV'!$E$2:$E$1000,'Kế hoạch'!$B$2) -> 13 | C7: =COUNTIFS('Chi tiết bảng NV'!$D$2:$D$1000,'Kế hoạch'!A7,'Chi tiết bảng NV'!$E$2:$E$1000,'Kế hoạch'!$C$2) -> 48 | D7: =COUNTIFS('Chi tiết bảng NV'!$D$2:$D$1000,'Kế hoạch'!A7,'Chi tiết bảng NV'!$E$2:$E$1000,'Kế hoạch'!$D$2) -> 5 | E7: =COUNTIFS('Chi tiết bảng NV'!$D$2:$D$1000,'Kế hoạch'!A7,'Chi tiết bảng NV'!$E$2:$E$1000,$E$2) -> 0 | F7: =SUM(B7:E7) -> 66 | H7: Đã thiết kế | I7: Done | J7: Done | K7: Done | L7: Done
A8: Thanh tra chứng khoán | B8: =COUNTIFS('Chi tiết bảng NV'!$D$2:$D$1000,'Kế hoạch'!A8,'Chi tiết bảng NV'!$E$2:$E$1000,'Kế hoạch'!$B$2) -> 0 | C8: =COUNTIFS('Chi tiết bảng NV'!$D$2:$D$1000,'Kế hoạch'!A8,'Chi tiết bảng NV'!$E$2:$E$1000,'Kế hoạch'!$C$2) -> 54 | D8: =COUNTIFS('Chi tiết bảng NV'!$D$2:$D$1000,'Kế hoạch'!A8,'Chi tiết bảng NV'!$E$2:$E$1000,'Kế hoạch'!$D$2) -> 2 | E8: =COUNTIFS('Chi tiết bảng NV'!$D$2:$D$1000,'Kế hoạch'!A8,'Chi tiết bảng NV'!$E$2:$E$1000,$E$2) -> 0 | F8: =SUM(B8:E8) -> 56 | H8: Đã thiết kế | I8: Done | J8: Done | K8: 46203 | L8: 46203
A9: Giám sát giao dịch chứng khoán (Q5) | B9: =COUNTIFS('Chi tiết bảng NV'!$D$2:$D$1000,'Kế hoạch'!A9,'Chi tiết bảng NV'!$E$2:$E$1000,'Kế hoạch'!$B$2) -> 2 | C9: =COUNTIFS('Chi tiết bảng NV'!$D$2:$D$1000,'Kế hoạch'!A9,'Chi tiết bảng NV'!$E$2:$E$1000,'Kế hoạch'!$C$2) -> 15 | D9: =COUNTIFS('Chi tiết bảng NV'!$D$2:$D$1000,'Kế hoạch'!A9,'Chi tiết bảng NV'!$E$2:$E$1000,'Kế hoạch'!$D$2) -> 7 | E9: =COUNTIFS('Chi tiết bảng NV'!$D$2:$D$1000,'Kế hoạch'!A9,'Chi tiết bảng NV'!$E$2:$E$1000,$E$2) -> 7 | F9: =SUM(B9:E9) -> 31 | G9: Chỉ thiết kế ATM, Không lên DTM | I9: 46203 | J9: 46203 | K9: 46209 | L9: 46210 | M9: =L9+1 -> 46211 | N9: =M9+3 -> 46214
A10: Giám sát giao dịch trực tuyến (Q3) | B10: =COUNTIFS('Chi tiết bảng NV'!$D$2:$D$1000,'Kế hoạch'!A10,'Chi tiết bảng NV'!$E$2:$E$1000,'Kế hoạch'!$B$2) -> 1 | C10: =COUNTIFS('Chi tiết bảng NV'!$D$2:$D$1000,'Kế hoạch'!A10,'Chi tiết bảng NV'!$E$2:$E$1000,'Kế hoạch'!$C$2) -> 7 | D10: =COUNTIFS('Chi tiết bảng NV'!$D$2:$D$1000,'Kế hoạch'!A10,'Chi tiết bảng NV'!$E$2:$E$1000,'Kế hoạch'!$D$2) -> 1 | E10: =COUNTIFS('Chi tiết bảng NV'!$D$2:$D$1000,'Kế hoạch'!A10,'Chi tiết bảng NV'!$E$2:$E$1000,$E$2) -> 0 | F10: =SUM(B10:E10) -> 9 | G10: Chỉ thiết kế ATM, Không lên DTM | I10: 46203 | J10: 46203 | K10: 46209 | L10: 46210 | M10: =L10+1 -> 46211 | N10: =M10+3 -> 46214
A11: Quản lý rủi ro TTCK (Q16) | B11: =COUNTIFS('Chi tiết bảng NV'!$D$2:$D$1000,'Kế hoạch'!A11,'Chi tiết bảng NV'!$E$2:$E$1000,'Kế hoạch'!$B$2) -> 4 | C11: =COUNTIFS('Chi tiết bảng NV'!$D$2:$D$1000,'Kế hoạch'!A11,'Chi tiết bảng NV'!$E$2:$E$1000,'Kế hoạch'!$C$2) -> 0 | D11: =COUNTIFS('Chi tiết bảng NV'!$D$2:$D$1000,'Kế hoạch'!A11,'Chi tiết bảng NV'!$E$2:$E$1000,'Kế hoạch'!$D$2) -> 2 | E11: =COUNTIFS('Chi tiết bảng NV'!$D$2:$D$1000,'Kế hoạch'!A11,'Chi tiết bảng NV'!$E$2:$E$1000,$E$2) -> 10 | F11: =SUM(B11:E11) -> 16 | G11: Dữ liệu chỉ tiêu, không thiết kế | I11: x | J11: x | K11: x | L11: x
A12: Thống kê nội bộ (Q15) | B12: =COUNTIFS('Chi tiết bảng NV'!$D$2:$D$1000,'Kế hoạch'!A12,'Chi tiết bảng NV'!$E$2:$E$1000,'Kế hoạch'!$B$2) -> 0 | C12: =COUNTIFS('Chi tiết bảng NV'!$D$2:$D$1000,'Kế hoạch'!A12,'Chi tiết bảng NV'!$E$2:$E$1000,'Kế hoạch'!$C$2) -> 0 | D12: =COUNTIFS('Chi tiết bảng NV'!$D$2:$D$1000,'Kế hoạch'!A12,'Chi tiết bảng NV'!$E$2:$E$1000,'Kế hoạch'!$D$2) -> 0 | E12: =COUNTIFS('Chi tiết bảng NV'!$D$2:$D$1000,'Kế hoạch'!A12,'Chi tiết bảng NV'!$E$2:$E$1000,$E$2) -> 17 | F12: =SUM(B12:E12) -> 17 | G12: Dữ liệu chỉ tiêu, không thiết kế | I12: x | J12: x | K12: x | L12: x
A13: Kết nối trao đổi dữ liệu (Q19) | B13: =COUNTIFS('Chi tiết bảng NV'!$D$2:$D$1000,'Kế hoạch'!A13,'Chi tiết bảng NV'!$E$2:$E$1000,'Kế hoạch'!$B$2) -> 0 | C13: =COUNTIFS('Chi tiết bảng NV'!$D$2:$D$1000,'Kế hoạch'!A13,'Chi tiết bảng NV'!$E$2:$E$1000,'Kế hoạch'!$C$2) -> 16 | D13: =COUNTIFS('Chi tiết bảng NV'!$D$2:$D$1000,'Kế hoạch'!A13,'Chi tiết bảng NV'!$E$2:$E$1000,'Kế hoạch'!$D$2) -> 0 | E13: =COUNTIFS('Chi tiết bảng NV'!$D$2:$D$1000,'Kế hoạch'!A13,'Chi tiết bảng NV'!$E$2:$E$1000,$E$2) -> 0 | F13: =SUM(B13:E13) -> 16 | G13: Chỉ thiết kế ATM, Không lên DTM | I13: 46203 | J13: 46203 | K13: 46209 | L13: 46210 | M13: =L13+1 -> 46211 | N13: =M13+3 -> 46214
A14: IDS | B14: =COUNTIFS('Chi tiết bảng NV'!$D$2:$D$1000,'Kế hoạch'!A14,'Chi tiết bảng NV'!$E$2:$E$1000,'Kế hoạch'!$B$2) -> 8 | C14: =COUNTIFS('Chi tiết bảng NV'!$D$2:$D$1000,'Kế hoạch'!A14,'Chi tiết bảng NV'!$E$2:$E$1000,'Kế hoạch'!$C$2) -> 48 | D14: =COUNTIFS('Chi tiết bảng NV'!$D$2:$D$1000,'Kế hoạch'!A14,'Chi tiết bảng NV'!$E$2:$E$1000,'Kế hoạch'!$D$2) -> 7 | E14: =COUNTIFS('Chi tiết bảng NV'!$D$2:$D$1000,'Kế hoạch'!A14,'Chi tiết bảng NV'!$E$2:$E$1000,$E$2) -> 11 | F14: =SUM(B14:E14) -> 74 | H14: Xong thiết kế mức bảng | I14: Done | J14: Done | K14: 46203 | L14: 46204 | M14: =L14+1 -> 46205 | N14: =M14+3 -> 46208
A15: Thủ tục hành chính (TTHC) | B15: =COUNTIFS('Chi tiết bảng NV'!$D$2:$D$1000,'Kế hoạch'!A15,'Chi tiết bảng NV'!$E$2:$E$1000,'Kế hoạch'!$B$2) -> 0 | C15: =COUNTIFS('Chi tiết bảng NV'!$D$2:$D$1000,'Kế hoạch'!A15,'Chi tiết bảng NV'!$E$2:$E$1000,'Kế hoạch'!$C$2) -> 0 | D15: =COUNTIFS('Chi tiết bảng NV'!$D$2:$D$1000,'Kế hoạch'!A15,'Chi tiết bảng NV'!$E$2:$E$1000,'Kế hoạch'!$D$2) -> 0 | E15: =COUNTIFS('Chi tiết bảng NV'!$D$2:$D$1000,'Kế hoạch'!A15,'Chi tiết bảng NV'!$E$2:$E$1000,$E$2) -> 0 | F15: =SUM(B15:E15) -> 0 | G15: Chỉ thiết kế ATM, Không lên DTM | I15: 46203 | J15: 46203 | K15: 46209 | L15: 46210 | M15: =L15+1 -> 46211 | N15: =M15+3 -> 46214
A16: Sổ lệnh, DL Thị trường, VSDC | G16: Không thiết kế, đẩy 1:1 hoặc chỉ tiêu động | I16: 46202 | J16: 46202 | K16: 46202 | L16: 46202 | M16: =L16+1 -> 46203 | N16: =M16+3 -> 46206
A17: TỔNG | B17: =SUM(B3:B15) -> 159 | C17: =SUM(C3:C15) -> 330 | D17: =SUM(D3:D15) -> 74 | E17: =SUM(E3:E15) -> 82 | F17: =SUM(F3:F15) -> 645
B19: Thiết kế bảng | D19: Thiết kế trường + mapping
A20: Thiết kế Datamart | B20: Start | C20: End | D20: Start | E20: End
A21: Giám sát CTCK (SCMS) | B21: =E22+2 -> 46216 | C21: =B21 -> 46216 | D21: =C21+1 -> 46217 | E21: =D21 -> 46217
A22: Giám sát CT QLQ & Quỹ ĐT (FMS) | B22: =B23+1 -> 46213 | C22: =B22 -> 46213 | D22: =C22+1 -> 46214 | E22: =D22 -> 46214
A23: Giám sát NĐT nước ngoài (FIMS) | B23: =D26+1 -> 46212 | C23: =B23 -> 46212 | D23: =C23 -> 46212 | E23: =D23 -> 46212
A24: Người hành nghề chứng khoán (NHNCK) | B24: Done | C24: Done | D24: Done | E24: Done
A25: Thanh tra chứng khoán | B25: =L8+1 -> 46204 | C25: =B25 -> 46204 | D25: 46204 | E25: 46204
A26: Giám sát giao dịch chứng khoán (Q5) | B26: =B29+1 -> 46210 | C26: =B26 -> 46210 | D26: =C26+1 -> 46211 | E26: =D26 -> 46211
A27: Quản lý rủi ro TTCK (Q16) | B27: =E21+1 -> 46218 | C27: =B27 -> 46218 | D27: =C27+1 -> 46219 | E27: =D27 -> 46219
A28: Thống kê nội bộ (Q15) | B28: =E31+1 -> 46224 | C28: =B28 -> 46224 | D28: =C28+1 -> 46225 | E28: =D28 -> 46225
A29: Quản lý chào bán | B29: =E30+3 -> 46209 | C29: =B29 -> 46209 | D29: =C29 -> 46209 | E29: =D29 -> 46209
A30: Quản lý công ty đại chúng | B30: =L14+1 -> 46205 | C30: =B30 -> 46205 | D30: =C30+1 -> 46206 | E30: =D30 -> 46206
A31: Văn phòng - Tổng hợp | B31: =D27+1 -> 46220 | C31: =B31 -> 46220 | D31: 46223 | E31: =D31 -> 46223
